ppg_package/__init__.py
ppg_package/analysis.py
ppg_package/area_calculation.py
ppg_package/autocorr.py
ppg_package/autocorr_analysis.py
ppg_package/distance_calculation.py
ppg_package/filter_ppg.py
ppg_package/model.py
ppg_package/notch_analysis.py
ppg_package/notch_analysis_ratio.py
ppg_package/period_analysis.py
ppg_package/plotter.py
ppg_package/ppgbreathing.py
ppg_package/s2_analysis.py
ppg_package/signal_analysis.py
ppg_package/slope_calculation.py
ppg_package/utils.py
tests/__init__.py
ppg_package-0.1.0.dist-info/LICENSE
ppg_package-0.1.0.dist-info/METADATA
ppg_package-0.1.0.dist-info/WHEEL
ppg_package-0.1.0.dist-info/top_level.txt
ppg_package-0.1.0.dist-info/RECORD
