Metadata-Version: 2.1
Name: ppg-package
Version: 0.1.0
Summary: A comprehensive package for processing and analyzing PPG signals
Home-page: https://github.com/zhuangjunyue/Deep-Learning-Network-for-Extracting-CO-from-PPG-Signals?tab=readme-ov-file
Author: JunYue Zhuang
Author-email: 1505472915@qq.com
License: MIT
Keywords: PPG,signal processing,analysis,FFT,PSD,CWT
Platform: UNKNOWN
Classifier: Development Status :: 3 - Alpha
Classifier: Intended Audience :: Science/Research
Classifier: Topic :: Scientific/Engineering :: Bio-Informatics
Classifier: License :: OSI Approved :: MIT License
Classifier: Programming Language :: Python :: 3
Classifier: Programming Language :: Python :: 3.7
Classifier: Programming Language :: Python :: 3.8
Classifier: Programming Language :: Python :: 3.9
Requires-Dist: numpy
Requires-Dist: matplotlib
Requires-Dist: scipy
Requires-Dist: PyWavelets
